sxd_master/__init__.py
sxd_master/build.py
sxd_master/main.py
sxd_master/trigger.py
sxd_master-0.1.0.dist-info/METADATA
sxd_master-0.1.0.dist-info/WHEEL
sxd_master-0.1.0.dist-info/entry_points.txt
sxd_master-0.1.0.dist-info/top_level.txt
sxd_master-0.1.0.dist-info/RECORD
