Metadata-Version: 2.4
Name: sxd-master
Version: 0.1.0
Summary: SXD Master Service for builds and triggers
Requires-Dist: sxd-core
Requires-Dist: fastapi>=0.95.0
Requires-Dist: uvicorn>=0.22.0
Requires-Dist: docker>=6.1.0
Requires-Dist: httpx>=0.23.0
Requires-Dist: pydantic>=2.0.0
Requires-Dist: python-multipart>=0.0.6
